konlpy_grpc/__init__.py
konlpy_grpc/__main__.py
konlpy_grpc/_generated/__init__.py
konlpy_grpc/_generated/global_pb2.py
konlpy_grpc/_generated/global_pb2_grpc.py
konlpy_grpc/_generated/hannanum_pb2.py
konlpy_grpc/_generated/hannanum_pb2_grpc.py
konlpy_grpc/_generated/kkma_pb2.py
konlpy_grpc/_generated/kkma_pb2_grpc.py
konlpy_grpc/_generated/komoran_pb2.py
konlpy_grpc/_generated/komoran_pb2_grpc.py
konlpy_grpc/_generated/mecab_pb2.py
konlpy_grpc/_generated/mecab_pb2_grpc.py
konlpy_grpc/_generated/okt_pb2.py
konlpy_grpc/_generated/okt_pb2_grpc.py
konlpy_grpc/client.py
konlpy_grpc/clients/__init__.py
konlpy_grpc/clients/hannanum_client.py
konlpy_grpc/clients/kkma_client.py
konlpy_grpc/clients/komoran_client.py
konlpy_grpc/clients/mecab_client.py
konlpy_grpc/clients/okt_client.py
konlpy_grpc/monkeypatch/__init__.py
konlpy_grpc/server.py
konlpy_grpc/servers/hannanum_server.py
konlpy_grpc/servers/kkma_server.py
konlpy_grpc/servers/komoran_server.py
konlpy_grpc/servers/mecab_server.py
konlpy_grpc/servers/okt_server.py
konlpy_grpc_gateway/README.md
konlpy_grpc-0.1.0.dist-info/LICENSE
konlpy_grpc-0.1.0.dist-info/WHEEL
konlpy_grpc-0.1.0.dist-info/METADATA
konlpy_grpc-0.1.0.dist-info/RECORD
