Metadata-Version: 2.1
Name: konlpy-grpc
Version: 0.1.0
Summary: Redesigned KoNLPy (Wrapper) for Usability and Portability with gRPC.
Home-page: https://github.com/minhoryang/KoNLPy-gRPC
License: GPL-3.0+
Author: Minho Ryang
Author-email: minhoryang@gmail.com
Requires-Python: >=3.6,<4.0
Classifier: License :: OSI Approved :: GNU General Public License v3 or later (GPLv3+)
Classifier: Programming Language :: Python :: 3
Classifier: Programming Language :: Python :: 3.6
Classifier: Programming Language :: Python :: 3.7
Provides-Extra: server
Requires-Dist: grpcio
Requires-Dist: grpcio-reflection
Requires-Dist: grpcio-tools
Requires-Dist: konlpy (>=0.5.2,<0.6.0); extra == "server"
Project-URL: Repository, https://github.com/minhoryang/KoNLPy-gRPC
